mandala/__init__.py
mandala/cf.py
mandala/common_imports.py
mandala/config.py
mandala/imports.py
mandala/model.py
mandala/storage.py
mandala/storage_utils.py
mandala/tps.py
mandala/utils.py
mandala/viz.py
mandala/deps/crawler.py
mandala/deps/deep_versions.py
mandala/deps/model.py
mandala/deps/shallow_versions.py
mandala/deps/utils.py
mandala/deps/versioner.py
mandala/deps/viz.py
mandala/deps/tracers/__init__.py
mandala/deps/tracers/dec_impl.py
mandala/deps/tracers/sys_impl.py
mandala/deps/tracers/tracer_base.py
mandala/tests/test_cfs.py
mandala/tests/test_memoization.py
mandala/tests/test_versioning.py
pymandala-0.2.0a0.dist-info/LICENSE
pymandala-0.2.0a0.dist-info/METADATA
pymandala-0.2.0a0.dist-info/WHEEL
pymandala-0.2.0a0.dist-info/top_level.txt
pymandala-0.2.0a0.dist-info/RECORD
