Metadata-Version: 2.1
Name: pymandala
Version: 0.2.0a0
Summary: A powerful and easy to use experiment tracking framework
Home-page: https://github.com/amakelov/mandala
Author: Aleksandar (Alex) Makelov
Author-email: aleksandar.makelov@gmail.com
License: Apache 2.0
Keywords: computational-experiments data-management machine-learning data-science
Classifier: Development Status :: 3 - Alpha
Classifier: Intended Audience :: Science/Research
Classifier: Operating System :: OS Independent
Classifier: License :: OSI Approved :: Apache Software License
Classifier: Programming Language :: Python :: 3
Classifier: Programming Language :: Python :: 3.10
Classifier: Programming Language :: Python :: 3.9
Classifier: Programming Language :: Python :: 3.8
Requires-Python: >=3.8
License-File: LICENSE
Requires-Dist: numpy>=1.18
Requires-Dist: pandas>=1.0
Requires-Dist: joblib>=1.0
Provides-Extra: base
Requires-Dist: prettytable; extra == "base"
Requires-Dist: graphviz; extra == "base"
Provides-Extra: ui
Requires-Dist: rich; extra == "ui"
Provides-Extra: test
Requires-Dist: pytest>=6.0.0; extra == "test"
Requires-Dist: hypothesis>=6.0.0; extra == "test"
Requires-Dist: ipython; extra == "test"
Provides-Extra: demos
Requires-Dist: scikit-learn; extra == "demos"
Provides-Extra: complete
Requires-Dist: graphviz; extra == "complete"
Requires-Dist: hypothesis>=6.0.0; extra == "complete"
Requires-Dist: ipython; extra == "complete"
Requires-Dist: prettytable; extra == "complete"
Requires-Dist: pytest>=6.0.0; extra == "complete"
Requires-Dist: rich; extra == "complete"
Requires-Dist: scikit-learn; extra == "complete"
